powerboxes-0.2.3.dist-info/METADATA
powerboxes-0.2.3.dist-info/WHEEL
powerboxes/__init__.py
powerboxes/_tiou.py
powerboxes/_nms.py
powerboxes/_diou.py
powerboxes/_giou.py
powerboxes/_iou.py
powerboxes/_boxes.py
powerboxes/_powerboxes.cpython-311-s390x-linux-gnu.so
powerboxes-0.2.3.dist-info/RECORD
