Metadata-Version: 2.3
Name: powerboxes
Version: 0.2.3
Classifier: Programming Language :: Rust
Classifier: Programming Language :: Python :: Implementation :: PyPy
Classifier: Programming Language :: Python :: Implementation :: CPython
Classifier: Programming Language :: Python :: 3.7
Classifier: Programming Language :: Python :: 3.8
Classifier: Programming Language :: Python :: 3.9
Classifier: Programming Language :: Python :: 3.10
Classifier: Programming Language :: Python :: 3.11
Classifier: Programming Language :: Python :: 3.12
Classifier: Programming Language :: Rust
Classifier: License :: OSI Approved :: MIT License
Classifier: Operating System :: POSIX :: Linux
Classifier: Operating System :: Microsoft :: Windows
Classifier: Operating System :: MacOS
Requires-Dist: numpy
Summary: Utility functions to manipulate and compute metrics on boxes
Home-Page: https://github.com/Smirkey/powerboxes
Author: Buillaume <guillaume.bertrand@edhec.com>
Author-email: Buillaume <guillaume.bertrand@edhec.com>
License: MIT
Requires-Python: >=3.7
Project-URL: Source Code, https://github.com/Smirkey/powerboxes
